{"abandoned": 389, "abandoned_30": 12, "abandoned_365": 320, "abandoned_7": 1, "closed": 1929, "closed_30": 81, "closed_365": 1696, "closed_7": 4, "diff_netabandoned_30": -24, "diff_netabandoned_365": 255, "diff_netabandoned_7": -3, "diff_netclosed_30": -73, "diff_netclosed_365": 1480, "diff_netclosed_7": -9, "diff_netmerged_30": -49, "diff_netmerged_365": 1225, "diff_netmerged_7": -6, "diff_netpending_30": -19, "diff_netpending_365": 230, "diff_netpending_7": 2, "diff_netsubmitted_30": -92, "diff_netsubmitted_365": 1710, "diff_netsubmitted_7": -7, "diff_netsubmitters_30": -19, "diff_netsubmitters_365": 119, "diff_netsubmitters_7": -2, "first_date": "2012-02-10", "inprogress": 0, "last_date": "2014-07-05", "merged": 1540, "merged_30": 69, "merged_365": 1376, "merged_7": 3, "new": 289, "opened": 289, "pending": 289, "pending_30": 40, "pending_365": 258, "pending_7": 10, "percentage_abandoned_30": 66, "percentage_abandoned_365": 392, "percentage_abandoned_7": 75, "percentage_closed_30": 47, "percentage_closed_365": 685, "percentage_closed_7": 69, "percentage_merged_30": 41, "percentage_merged_365": 811, "percentage_merged_7": 66, "percentage_pending_30": 32, "percentage_pending_365": 821, "percentage_pending_7": 25, "percentage_submitted_30": 43, "percentage_submitted_365": 700, "percentage_submitted_7": 33, "percentage_submitters_30": 38, "percentage_submitters_365": 340, "percentage_submitters_7": 16, "repositories": 138, "review_time_days_avg": 22.064576433785227, "review_time_days_median": 3.793, "reviewers": 898, "submitted": 2218, "submitted_30": 121, "submitted_365": 1954, "submitted_7": 14, "submitters": 168, "submitters_30": 31, "submitters_365": 154, "submitters_7": 10}