{"changed": 6144, "changers": 201, "closed": 5073, "closed_30": 77, "closed_365": 1610, "closed_7": 22, "closers": 57, "closers_30": 14, "closers_365": 31, "closers_7": 10, "diff_netclosed_30": -50, "diff_netclosed_365": 470, "diff_netclosed_7": -5, "diff_netclosers_30": -1, "diff_netclosers_365": 5, "diff_netclosers_7": 1, "first_date": "2010-12-06", "last_date": "2014-06-11", "opened": 6546, "openers": 179, "percentage_closed_30": 39, "percentage_closed_365": 41, "percentage_closed_7": 18, "percentage_closers_30": 6, "percentage_closers_365": 19, "percentage_closers_7": 11, "trackers": 1}