{"diff_netsenders_30": -34, "diff_netsenders_365": 5, "diff_netsenders_7": 0, "diff_netsent_30": -151, "diff_netsent_365": 97, "diff_netsent_7": 0, "first_date": "2001-11-01", "last_date": "2014-06-04", "percentage_senders_30": 62, "percentage_senders_365": 2, "percentage_senders_7": 0, "percentage_sent_30": 57, "percentage_sent_365": 2, "percentage_sent_7": 0, "repositories": 15, "senders": 4197, "senders_30": 20, "senders_365": 224, "senders_7": 0, "senders_init": 3824, "senders_response": 1710, "sent": 68400, "sent_30": 110, "sent_365": 3664, "sent_7": 0, "sent_response": 26880, "threads": 21987}