{"changed": 50996, "changers": 5286, "closed": 46620, "closed_30": 52, "closed_365": 1502, "closed_7": 12, "closers": 1096, "closers_30": 13, "closers_365": 61, "closers_7": 7, "diff_netclosed_30": -51, "diff_netclosed_365": 264, "diff_netclosed_7": 6, "diff_netclosers_30": -4, "diff_netclosers_365": -5, "diff_netclosers_7": 3, "first_date": "2001-10-10", "last_date": "2014-06-29", "opened": 51425, "openers": 8358, "percentage_closed_30": 49, "percentage_closed_365": 21, "percentage_closed_7": 100, "percentage_closers_30": 23, "percentage_closers_365": 7, "percentage_closers_7": 75, "trackers": 1}