{"changed": 7, "changers": 2, "closed": 2, "closed_30": 0, "closed_365": 0, "closed_7": 0, "closers": 1, "closers_30": 0, "closers_365": 0, "closers_7": 0, "diff_netclosed_30": 0, "diff_netclosed_365": 0, "diff_netclosed_7": 0, "diff_netclosers_30": 0, "diff_netclosers_365": 0, "diff_netclosers_7": 0, "first_date": "2009-07-29", "last_date": "2013-09-12", "opened": 11, "openers": 3, "percentage_closed_30": 0, "percentage_closed_365": 0, "percentage_closed_7": 0, "percentage_closers_30": 0, "percentage_closers_365": 0, "percentage_closers_7": 0, "trackers": 7}