{"diff_netsenders_30": 0, "diff_netsenders_365": -6, "diff_netsenders_7": 6, "diff_netsent_30": -46, "diff_netsent_365": -120, "diff_netsent_7": 5, "first_date": "2001-11-01", "last_date": "2014-07-11", "percentage_senders_30": 0, "percentage_senders_365": 8, "percentage_senders_7": 46, "percentage_sent_30": 21, "percentage_sent_365": 5, "percentage_sent_7": 11, "repositories": 156, "senders": 221, "senders_30": 34, "senders_365": 68, "senders_7": 19, "senders_init": 211, "senders_response": 193, "sent": 37630, "sent_30": 172, "sent_365": 2153, "sent_7": 50, "sent_response": 22333, "threads": 20242}