{"abandoned": 1048, "abandoned_30": 13, "abandoned_365": 354, "abandoned_7": 0, "closed": 6519, "closed_30": 171, "closed_365": 2809, "closed_7": 40, "diff_netabandoned_30": -30, "diff_netabandoned_365": 133, "diff_netabandoned_7": -4, "diff_netclosed_30": -185, "diff_netclosed_365": 1314, "diff_netclosed_7": -13, "diff_netmerged_30": -155, "diff_netmerged_365": 1181, "diff_netmerged_7": -9, "diff_netpending_30": -16, "diff_netpending_365": 135, "diff_netpending_7": 12, "diff_netsubmitted_30": -201, "diff_netsubmitted_365": 1449, "diff_netsubmitted_7": -1, "diff_netsubmitters_30": 3, "diff_netsubmitters_365": 21, "diff_netsubmitters_7": 2, "first_date": "2012-02-10", "inprogress": 0, "last_date": "2014-07-11", "merged": 5471, "merged_30": 158, "merged_365": 2455, "merged_7": 40, "new": 236, "opened": 236, "pending": 236, "pending_30": 35, "pending_365": 177, "pending_7": 19, "percentage_abandoned_30": 69, "percentage_abandoned_365": 60, "percentage_abandoned_7": 100, "percentage_closed_30": 51, "percentage_closed_365": 87, "percentage_closed_7": 24, "percentage_merged_30": 49, "percentage_merged_365": 92, "percentage_merged_7": 18, "percentage_pending_30": 31, "percentage_pending_365": 321, "percentage_pending_7": 171, "percentage_submitted_30": 49, "percentage_submitted_365": 94, "percentage_submitted_7": 1, "percentage_submitters_30": 8, "percentage_submitters_365": 35, "percentage_submitters_7": 10, "repositories": 139, "review_time_days_avg": 233.5021480288881, "review_time_days_median": 186.9899, "reviewers": 907, "submitted": 6755, "submitted_30": 206, "submitted_365": 2986, "submitted_7": 59, "submitters": 109, "submitters_30": 40, "submitters_365": 81, "submitters_7": 21}