{"authors": 27, "authors_30": 13, "authors_365": 18, "authors_7": 10, "avg_commits_author": 729.8889, "avg_commits_month": 243.2963, "commits": 19707, "commits_30": 261, "commits_365": 2519, "commits_7": 71, "committers": 26, "diff_netauthors_30": 1, "diff_netauthors_365": 0, "diff_netauthors_7": 3, "diff_netcommits_30": 11, "diff_netcommits_365": -637, "diff_netcommits_7": 30, "files": 90623, "first_date": "2001-05-02", "last_date": "2014-06-30", "percentage_authors_30": 8, "percentage_authors_365": 0, "percentage_authors_7": 42, "percentage_commits_30": 4, "percentage_commits_365": 20, "percentage_commits_7": 73, "repositories": 24}