{"closers.": {"closed": [15607, 13317, 10489, 10372, 7846, 7362, 6534, 6391, 5343, 4681], "closers": ["Dani Megert", "Tod_Creasey@ca.ibm.com", "darin.eclipse@gmail.com", "aeschli@gmail.com", "dbaeumer", "johna", "Paul Webster", "Michael Valenta", "Markus Keller", "Steffen Pingel"], "id": [607, 4270, 3184, 3226, 1374, 572, 571, 2130, 612, 802]}, "closers.last month": {"closed": [286, 185, 68, 47, 45, 40, 38, 38, 38, 36], "closers": ["Lars Vogel", "Camille Letavernier", "david_williams", "Michael Rennie", "Srikanth Sankaran", "Paul Webster", "ahunter", "Dave Russo", "Linda Chan", "Daniel Rolka"], "id": [593, 2041, 61, 405, 1312, 571, 976, 14280, 102, 639]}, "closers.last year": {"closed": [1137, 838, 597, 585, 524, 475, 410, 408, 400, 340], "closers": ["Dani Megert", "Paul Webster", "Camille Letavernier", "Lars Vogel", "david_williams", "Eike Stepper", "Michael Rennie", "Srikanth Sankaran", "Thomas Watson", "Oliver Goetz"], "id": [607, 571, 2041, 593, 61, 289, 405, 1312, 1023, 10010]}, "openers.": {"id": [607, 612, 572, 3859, 4270, 61, 3226, 1390, 3184, 1018], "opened": [7723, 6780, 4378, 4112, 3933, 3323, 3199, 3133, 3070, 3009], "openers": ["Dani Megert", "Markus Keller", "johna", "nick_edgar@ca.ibm.com", "Tod_Creasey@ca.ibm.com", "david_williams", "aeschli@gmail.com", "Adam Kiezun", "darin.eclipse@gmail.com", "Pascal Rapicault (JBoss)"]}, "openers.last month": {"id": [593, 61, 612, 303, 16369, 976, 405, 1312, 62, 1014], "opened": [149, 67, 43, 42, 35, 33, 29, 25, 24, 22], "openers": ["Lars Vogel", "david_williams", "Markus Keller", "Ed.Willink", "Ronan B", "ahunter", "Michael Rennie", "Srikanth Sankaran", "Stephan Herrmann", "Markus Tiede"]}, "openers.last year": {"id": [61, 593, 607, 303, 1942, 612, 571, 1014, 405, 1312], "opened": [557, 528, 423, 414, 355, 354, 244, 242, 240, 211], "openers": ["david_williams", "Lars Vogel", "Dani Megert", "Ed.Willink", "Mark Macdonald", "Markus Keller", "Paul Webster", "Markus Tiede", "Michael Rennie", "Srikanth Sankaran"]}}