{"closers.": {"closed": [15768, 13317, 10489, 10372, 7846, 7363, 6688, 6391, 5440, 4681], "closers": ["Dani Megert", "Tod_Creasey@ca.ibm.com", "darin.eclipse@gmail.com", "aeschli@gmail.com", "Dirk Baeumer", "John_Arthorne@ca.ibm.com", "E4 Build", "Michael Valenta", "mkeller", "spingel"], "id": [183, 4412, 3330, 3372, 182, 411, 202, 659, 197, 527]}, "closers.last month": {"closed": [162, 84, 80, 78, 62, 60, 56, 54, 54, 51], "closers": ["Lars Vogel", "Dani Megert", "E4 Build", "david_williams@us.ibm.com", "Scott Lewis", "Camille Letavernier", "Eugen Neufeld", "mkeller", "Pierre-Charles David", "Kentarou Fukuda"], "id": [276, 183, 202, 273, 3080, 1345, 108, 197, 556, 1501]}, "closers.last year": {"closed": [1045, 858, 816, 616, 505, 432, 404, 385, 374, 365], "closers": ["Dani Megert", "Lars Vogel", "E4 Build", "Camille Letavernier", "david_williams@us.ibm.com", "Eike Stepper", "mrennie", "ssankaran", "Thomas Watson", "Stephan Herrmann"], "id": [183, 276, 202, 1345, 273, 172, 610, 3025, 589, 262]}, "openers.": {"id": [183, 197, 411, 4003, 4412, 273, 3372, 670, 179, 3330], "opened": [7776, 6845, 4384, 4112, 3933, 3405, 3199, 3158, 3133, 3070], "openers": ["Dani Megert", "mkeller", "John_Arthorne@ca.ibm.com", "nick_edgar@ca.ibm.com", "Tod_Creasey@ca.ibm.com", "david_williams@us.ibm.com", "aeschli@gmail.com", "Pascal Rapicault", "akiezun", "darin.eclipse@gmail.com"]}, "openers.last month": {"id": [276, 273, 197, 2073, 290, 219, 271, 183, 2318, 432], "opened": [62, 47, 39, 38, 37, 35, 33, 31, 31, 29], "openers": ["Lars Vogel", "david_williams@us.ibm.com", "mkeller", "Andreas Sewe", "Thomas Schindl", "Ed.Willink", "Noopur Gupta", "Dani Megert", "Johannes Dorn", "ahunter"]}, "openers.last year": {"id": [276, 273, 219, 183, 197, 416, 610, 1866, 202, 262], "opened": [658, 532, 441, 400, 349, 333, 242, 239, 230, 219], "openers": ["Lars Vogel", "david_williams@us.ibm.com", "Ed.Willink", "Dani Megert", "mkeller", "Mark Macdonald", "mrennie", "Markus Tiede", "E4 Build", "Stephan Herrmann"]}}