{"actions": 474792, "authors": 68, "authors_30": 7, "authors_365": 25, "authors_7": 0, "avg_commits_author": 388.0735, "avg_commits_month": 216.3033, "avg_files_author": 2460.5147, "avg_files_month": 1371.4344, "branches": 86, "commits": 26389, "commits_30": 21, "commits_365": 1556, "commits_7": 0, "committers": 56, "diff_netauthors_30": -2, "diff_netauthors_365": 7, "diff_netauthors_7": -2, "diff_netcommits_30": -17, "diff_netcommits_365": -225, "diff_netcommits_7": -2, "diff_netfiles_30": -823, "diff_netfiles_365": -13677, "diff_netfiles_7": -3, "files": 167315, "files_30": 159, "files_365": 19189, "files_7": 0, "first_date": "2001-05-02", "last_date": "2014-05-26", "percentage_authors_30": 22, "percentage_authors_365": 38, "percentage_authors_7": 100, "percentage_commits_30": 44, "percentage_commits_365": 12, "percentage_commits_7": 100, "percentage_files_30": 83, "percentage_files_365": 41, "percentage_files_7": 100, "repositories": 9}