{"abandoned": 415, "abandoned_30": 2, "abandoned_365": 117, "abandoned_7": 0, "closed": 1982, "closed_30": 43, "closed_365": 900, "closed_7": 17, "diff_netabandoned_30": -2, "diff_netabandoned_365": -90, "diff_netabandoned_7": 0, "diff_netclosed_30": -7, "diff_netclosed_365": -3, "diff_netclosed_7": 12, "diff_netmerged_30": -5, "diff_netmerged_365": 87, "diff_netmerged_7": 12, "diff_netpending_30": 3, "diff_netpending_365": 29, "diff_netpending_7": 2, "diff_netsubmitted_30": -4, "diff_netsubmitted_365": 26, "diff_netsubmitted_7": 14, "diff_netsubmitters_30": -1, "diff_netsubmitters_365": 5, "diff_netsubmitters_7": 3, "first_date": "2012-02-10", "inprogress": 0, "last_date": "2014-07-08", "merged": 1567, "merged_30": 41, "merged_365": 783, "merged_7": 17, "new": 84, "opened": 84, "pending": 84, "pending_30": 7, "pending_365": 55, "pending_7": 2, "percentage_abandoned_30": 50, "percentage_abandoned_365": 43, "percentage_abandoned_7": 0, "percentage_closed_30": 14, "percentage_closed_365": 0, "percentage_closed_7": 240, "percentage_merged_30": 10, "percentage_merged_365": 12, "percentage_merged_7": 240, "percentage_pending_30": 75, "percentage_pending_365": 111, "percentage_pending_7": 0, "percentage_submitted_30": 7, "percentage_submitted_365": 2, "percentage_submitted_7": 280, "percentage_submitters_30": 8, "percentage_submitters_365": 14, "percentage_submitters_7": 100, "repositories": 138, "review_time_days_avg": 77.64850544554463, "review_time_days_median": 9.34655, "reviewers": 902, "submitted": 2066, "submitted_30": 50, "submitted_365": 955, "submitted_7": 19, "submitters": 58, "submitters_30": 11, "submitters_365": 39, "submitters_7": 6}