{"changed": 2341, "changers": 29, "closed": 1387, "closed_30": 43, "closed_365": 265, "closed_7": 29, "closers": 25, "closers_30": 8, "closers_365": 16, "closers_7": 3, "diff_netclosed_30": -21, "diff_netclosed_365": 4, "diff_netclosed_7": 26, "diff_netclosers_30": -2, "diff_netclosers_365": 5, "diff_netclosers_7": 1, "first_date": "2003-03-04", "last_date": "2014-06-26", "opened": 1312, "openers": 30, "percentage_closed_30": 32, "percentage_closed_365": 1, "percentage_closed_7": 866, "percentage_closers_30": 19, "percentage_closers_365": 45, "percentage_closers_7": 50, "trackers": 61}