{"actions": 26814, "authors": 38, "authors_30": 12, "authors_365": 34, "authors_7": 0, "avg_commits_author": 75.7368, "avg_commits_month": 70.1951, "avg_files_author": 247.3158, "avg_files_month": 229.2195, "branches": 17, "commits": 2878, "commits_30": 68, "commits_365": 707, "commits_7": 0, "committers": 18, "diff_netauthors_30": -3, "diff_netauthors_365": 8, "diff_netauthors_7": -5, "diff_netcommits_30": 6, "diff_netcommits_365": -130, "diff_netcommits_7": -26, "diff_netfiles_30": 431, "diff_netfiles_365": 300, "diff_netfiles_7": -380, "files": 9398, "files_30": 858, "files_365": 4405, "files_7": 0, "first_date": "2001-05-02", "last_date": "2014-05-26", "percentage_authors_30": 19, "percentage_authors_365": 30, "percentage_authors_7": 100, "percentage_commits_30": 9, "percentage_commits_365": 15, "percentage_commits_7": 100, "percentage_files_30": 100, "percentage_files_365": 7, "percentage_files_7": 100, "repositories": 1}