{"authors": ["Eric Gwin", "tware", "Blaise Doughan", "Guy Pelletier", "Edwin Tang", "Mike Norman", "Matt MacIvor", "David McCann", "Denise Smith", "Rick Barkhouse", "dclarke", "ailitche", "jsutherla", "Gordon Yorke", "desmith", "Peter Krogh", "Michael O'Brien", "Yiping Zhao", "Chris Delahunt", "Kevin Yuan", "Gul Onural", "David Minsky", "pfilion", "Les Davis", "Adrian Goerler", "Shaun Smith", "Vikram Bhatia", "Mitesh Meswani", "Kyle Chen", "Sabine Heider", "David Twelves", "Mike Keith", "johnbracken", "Tomas Kraus", "nhauge", "Lukas Jungmann", "Andreas Fischbach", "Rick Curtis", "Rick Sapir", "Martin Grebac", "Mythily Parthasarathy", "Peter Purich", "Liza Rekadze", "Peter Benedikovic", "Marcel Valovy", "mnorman", "Bo Liu"], "commits": [1907, 1303, 840, 838, 804, 797, 690, 675, 582, 574, 520, 485, 464, 381, 337, 306, 303, 296, 273, 229, 227, 226, 178, 163, 92, 89, 74, 56, 44, 23, 21, 20, 20, 15, 13, 13, 12, 8, 3, 3, 3, 1, 1, 1, 1, 1, 1], "companies": ["Oracle", "individual", "Scapa Technologies Limited", "SAP AG"], "company_commits": [12454, 1306, 798, 104], "id": [62, 37, 45, 50, 60, 43, 44, 38, 40, 52, 36, 54, 53, 51, 71, 49, 41, 64, 56, 63, 81, 55, 68, 59, 66, 58, 69, 61, 48, 85, 39, 65, 3170, 86, 57, 90, 67, 84, 46, 87, 88, 42, 47, 89, 91, 580, 3273]}