{"actions": 97319, "authors": 24, "authors_365": 11, "avg_commits_author": 397.0833, "avg_commits_month": 153.7097, "avg_files_author": 440.0, "avg_files_month": 170.3226, "branches": 9, "commits": 9530, "commits_365": 2118, "committers": 15, "diff_netauthors_30": 0, "diff_netauthors_365": 0, "diff_netauthors_7": 0, "diff_netcommits_30": 6, "diff_netcommits_365": -603, "diff_netcommits_7": -11, "diff_netfiles_30": 14, "diff_netfiles_365": 2991, "diff_netfiles_7": -25, "files": 10560, "first_date": "2009-03-16", "last_date": "2014-05-25", "percentage_authors_30": 0, "percentage_authors_365": 0, "percentage_authors_7": 0, "percentage_commits_30": 3, "percentage_commits_365": 22, "percentage_commits_7": 30, "percentage_files_30": 2, "percentage_files_365": 80, "percentage_files_7": 14, "repositories": 5}