{"authors": 2405, "authors_30": 370, "authors_365": 968, "authors_7": 201, "avg_commits_author": 368.4777, "avg_commits_month": 5625.7389, "commits": 883241, "commits_30": 5493, "commits_365": 59981, "commits_7": 932, "committers": 1827, "companies": 95, "core": 316, "diff_netauthors_30": -12, "diff_netauthors_365": 27, "diff_netauthors_7": -7, "diff_netcommits_30": 692, "diff_netcommits_365": -15587, "diff_netcommits_7": -335, "files": 4557694, "first_date": "2001-05-02", "last_date": "2014-06-11", "occasional": 1701, "percentage_authors_30": 3, "percentage_authors_365": 2, "percentage_authors_7": 3, "percentage_commits_30": 14, "percentage_commits_365": 20, "percentage_commits_7": 26, "regular": 380, "repositories": 422, "type": "git", "url": "http://git.eclipse.org/gitroot/koneki/org.eclipse.koneki.ldt.git"}