{"authors": 2410, "authors_30": 356, "authors_365": 969, "authors_7": 155, "avg_commits_author": 367.8447, "avg_commits_month": 5627.7898, "commits": 883563, "commits_30": 5041, "commits_365": 59668, "commits_7": 763, "committers": 1829, "companies": 95, "diff_netauthors_30": -46, "diff_netauthors_365": 29, "diff_netauthors_7": -60, "diff_netcommits_30": -164, "diff_netcommits_365": -15572, "diff_netcommits_7": -643, "files": 4558566, "first_date": "2001-05-02", "last_date": "2014-06-14", "percentage_authors_30": 11, "percentage_authors_365": 3, "percentage_authors_7": 27, "percentage_commits_30": 3, "percentage_commits_365": 20, "percentage_commits_7": 45, "repositories": 422, "type": "git", "url": "http://git.eclipse.org/gitroot/koneki/org.eclipse.koneki.ldt.git"}