{"authors": 2425, "authors_30": 345, "authors_365": 977, "authors_7": 169, "avg_commits_author": 366.2586, "avg_commits_month": 5638.5159, "commits": 885247, "commits_30": 3847, "commits_365": 59141, "commits_7": 812, "committers": 1840, "companies": 96, "core": 316, "diff_netauthors_30": -40, "diff_netauthors_365": 41, "diff_netauthors_7": 25, "diff_netcommits_30": -1484, "diff_netcommits_365": -14613, "diff_netcommits_7": 139, "files": 4565613, "first_date": "2001-05-02", "last_date": "2014-06-30", "occasional": 1720, "percentage_authors_30": 10, "percentage_authors_365": 4, "percentage_authors_7": 17, "percentage_commits_30": 27, "percentage_commits_365": 19, "percentage_commits_7": 20, "regular": 381, "repositories": 422, "type": "git", "url": "http://git.eclipse.org/gitroot/koneki/org.eclipse.koneki.ldt.git"}