{"authors": 13, "authors_30": 5, "authors_365": 13, "authors_7": 2, "avg_commits_author": 15.5385, "avg_commits_month": 33.6667, "commits": 202, "commits_30": 53, "commits_365": 202, "commits_7": 18, "committers": 11, "diff_netauthors_30": -2, "diff_netauthors_365": 13, "diff_netauthors_7": -1, "diff_netcommits_30": 14, "diff_netcommits_365": 202, "diff_netcommits_7": 10, "files": 1588, "first_date": "2001-05-02", "last_date": "2014-07-11", "percentage_authors_30": 28, "percentage_authors_365": 0, "percentage_authors_7": 33, "percentage_commits_30": 35, "percentage_commits_365": 0, "percentage_commits_7": 125, "repositories": 1}