{"abandoned": 1702, "abandoned_30": 35, "abandoned_365": 542, "abandoned_7": 2, "closed": 12698, "closed_30": 335, "closed_365": 4433, "closed_7": 36, "diff_netabandoned_30": -30, "diff_netabandoned_365": 215, "diff_netabandoned_7": -8, "diff_netclosed_30": -137, "diff_netclosed_365": 1767, "diff_netclosed_7": -24, "diff_netmerged_30": -107, "diff_netmerged_365": 1552, "diff_netmerged_7": -16, "diff_netpending_30": 49, "diff_netpending_365": 152, "diff_netpending_7": 11, "diff_netsubmitted_30": -88, "diff_netsubmitted_365": 1919, "diff_netsubmitted_7": -13, "diff_netsubmitters_30": 4, "diff_netsubmitters_365": 81, "diff_netsubmitters_7": -5, "inprogress": 0, "merged": 10996, "merged_30": 300, "merged_365": 3891, "merged_7": 34, "new": 346, "opened": 346, "pending": 346, "pending_30": 70, "pending_365": 212, "pending_7": 30, "percentage_abandoned_30": 46, "percentage_abandoned_365": 65, "percentage_abandoned_7": 80, "percentage_closed_30": 29, "percentage_closed_365": 66, "percentage_closed_7": 40, "percentage_merged_30": 26, "percentage_merged_365": 66, "percentage_merged_7": 31, "percentage_pending_30": 233, "percentage_pending_365": 253, "percentage_pending_7": 57, "percentage_submitted_30": 17, "percentage_submitted_365": 70, "percentage_submitted_7": 16, "percentage_submitters_30": 6, "percentage_submitters_365": 55, "percentage_submitters_7": 16, "repositories": 138, "review_time_days_avg": 310.32700490402834, "review_time_days_median": 482.3445, "reviewers": 888, "submitted": 13044, "submitted_30": 405, "submitted_365": 4645, "submitted_7": 66, "submitters": 377, "submitters_30": 69, "submitters_365": 226, "submitters_7": 25}