{"authors": 41, "authors_30": 5, "authors_365": 20, "authors_7": 4, "avg_commits_author": 25.4878, "avg_commits_month": 31.6667, "commits": 1045, "commits_30": 28, "commits_365": 238, "commits_7": 7, "committers": 15, "diff_netauthors_30": 2, "diff_netauthors_365": 8, "diff_netauthors_7": 0, "diff_netcommits_30": 7, "diff_netcommits_365": -59, "diff_netcommits_7": -8, "files": 4786, "first_date": "2001-05-02", "last_date": "2014-07-11", "percentage_authors_30": 66, "percentage_authors_365": 66, "percentage_authors_7": 0, "percentage_commits_30": 33, "percentage_commits_365": 19, "percentage_commits_7": 53, "repositories": 5}