{"abandoned": 600, "abandoned_30": 33, "abandoned_365": 305, "abandoned_7": 7, "closed": 4438, "closed_30": 226, "closed_365": 2299, "closed_7": 26, "diff_netabandoned_30": 17, "diff_netabandoned_365": 24, "diff_netabandoned_7": 3, "diff_netclosed_30": 24, "diff_netclosed_365": 230, "diff_netclosed_7": -53, "diff_netmerged_30": 7, "diff_netmerged_365": 206, "diff_netmerged_7": -56, "diff_netpending_30": 7, "diff_netpending_365": 112, "diff_netpending_7": 3, "diff_netsubmitted_30": 31, "diff_netsubmitted_365": 342, "diff_netsubmitted_7": -50, "diff_netsubmitters_30": 11, "diff_netsubmitters_365": 52, "diff_netsubmitters_7": -1, "inprogress": 0, "merged": 3838, "merged_30": 193, "merged_365": 1994, "merged_7": 19, "new": 200, "opened": 200, "pending": 200, "pending_30": 38, "pending_365": 153, "pending_7": 11, "percentage_abandoned_30": 106, "percentage_abandoned_365": 8, "percentage_abandoned_7": 75, "percentage_closed_30": 11, "percentage_closed_365": 11, "percentage_closed_7": 67, "percentage_merged_30": 3, "percentage_merged_365": 11, "percentage_merged_7": 74, "percentage_pending_30": 22, "percentage_pending_365": 273, "percentage_pending_7": 37, "percentage_submitted_30": 13, "percentage_submitted_365": 16, "percentage_submitted_7": 57, "percentage_submitters_30": 33, "percentage_submitters_365": 68, "percentage_submitters_7": 5, "repositories": 138, "review_time_days_avg": 97.49834968918351, "review_time_days_median": 48.2174, "reviewers": 878, "submitted": 4638, "submitted_30": 264, "submitted_365": 2452, "submitted_7": 37, "submitters": 159, "submitters_30": 44, "submitters_365": 128, "submitters_7": 18}